[
{
    "name": "Enim quisque augue.",
    "ipfsImage": "https://source.unsplash.com/user/erondu/200x300",
    "hair": "lightcoral",
    "skin": "sienna"
},
{
    "name": "Elementum vitae ac.",
    "ipfsImage": "https://source.unsplash.com/user/erondu/200x300",
    "hair": "darkturquoise",
    "skin": "aquamarine"
},
{
    "name": "Auctor id justo.",
    "ipfsImage": "https://source.unsplash.com/user/erondu/200x300",
    "hair": "darkseagreen",
    "skin": "darkkhaki"
},
{
    "name": "Mi ultrices hendrerit.",
    "ipfsImage": "https://source.unsplash.com/user/erondu/200x300",
    "hair": "gainsboro",
    "skin": "plum"
},
{
    "name": "Lobortis mi ali.",
    "ipfsImage": "https://source.unsplash.com/user/erondu/200x300",
    "hair": "olivedrab",
    "skin": "hotpink"
},
{
    "name": "Vel cras ex.",
    "ipfsImage": "https://source.unsplash.com/user/erondu/200x300",
    "hair": "orchid",
    "skin": "palevioletred"
},
{
    "name": "Lectus commodo cursus.",
    "ipfsImage": "https://source.unsplash.com/user/erondu/200x300",
    "hair": "skyblue",
    "skin": "snow"
},
{
    "name": "Rhoncus auctor elit.",
    "ipfsImage": "https://source.unsplash.com/user/erondu/200x300",
    "hair": "mistyrose",
    "skin": "mediumspringgreen"
},
{
    "name": "Posuere aliquam iaculis.",
    "ipfsImage": "https://source.unsplash.com/user/erondu/200x300",
    "hair": "darkviolet",
    "skin": "lightcyan"
},
{
    "name": "Aenean sollicitudin id.",
    "ipfsImage": "https://source.unsplash.com/user/erondu/200x300",
    "hair": "mediumorchid",
    "skin": "blanchedalmond"
},
{
    "name": "Vitae posuere dolor.",
    "ipfsImage": "https://source.unsplash.com/user/erondu/200x300",
    "hair": "palegreen",
    "skin": "forestgreen"
},
{
    "name": "Non elit accumsan.",
    "ipfsImage": "https://source.unsplash.com/user/erondu/200x300",
    "hair": "darkgoldenrod",
    "skin": "royalblue"
},
{
    "name": "Ipsum e nam.",
    "ipfsImage": "https://source.unsplash.com/user/erondu/200x300",
    "hair": "lightcoral",
    "skin": "brown"
},
{
    "name": "Eros it auctor.",
    "ipfsImage": "https://source.unsplash.com/user/erondu/200x300",
    "hair": "brown",
    "skin": "chartreuse"
},
{
    "name": "Pretium it vel.",
    "ipfsImage": "https://source.unsplash.com/user/erondu/200x300",
    "hair": "darkgray",
    "skin": "azure"
},
{
    "name": "Mollis el vestibulum.",
    "ipfsImage": "https://source.unsplash.com/user/erondu/200x300",
    "hair": "mediumseagreen",
    "skin": "teal"
},
{
    "name": "Tempus augue consequat.",
    "ipfsImage": "https://source.unsplash.com/user/erondu/200x300",
    "hair": "darkkhaki",
    "skin": "goldenrod"
},
{
    "name": "Magna o sagittis.",
    "ipfsImage": "https://source.unsplash.com/user/erondu/200x300",
    "hair": "mediumspringgreen",
    "skin": "navy"
},
{
    "name": "Eu est porttitor.",
    "ipfsImage": "https://source.unsplash.com/user/erondu/200x300",
    "hair": "seashell",
    "skin": "tan"
},
{
    "name": "Hendrerit neque orci.",
    "ipfsImage": "https://source.unsplash.com/user/erondu/200x300",
    "hair": "palegoldenrod",
    "skin": "brown"
},
{
    "name": "Maecenas nisi nisl.",
    "ipfsImage": "https://source.unsplash.com/user/erondu/200x300",
    "hair": "darkviolet",
    "skin": "darkcyan"
},
{
    "name": "Natoque ex lacinia.",
    "ipfsImage": "https://source.unsplash.com/user/erondu/200x300",
    "hair": "plum",
    "skin": "yellowgreen"
},
{
    "name": "Cit ante sapien.",
    "ipfsImage": "https://source.unsplash.com/user/erondu/200x300",
    "hair": "whitesmoke",
    "skin": "black"
},
{
    "name": "Tincidunt maecenas cras.",
    "ipfsImage": "https://source.unsplash.com/user/erondu/200x300",
    "hair": "steelblue",
    "skin": "gray"
},
{
    "name": "Dictum en eu.",
    "ipfsImage": "https://source.unsplash.com/user/erondu/200x300",
    "hair": "white",
    "skin": "seagreen"
},
{
    "name": "Sagittis nulla a.",
    "ipfsImage": "https://source.unsplash.com/user/erondu/200x300",
    "hair": "orange",
    "skin": "lightskyblue"
},
{
    "name": "Ipsum enim dolor.",
    "ipfsImage": "https://source.unsplash.com/user/erondu/200x300",
    "hair": "saddlebrown",
    "skin": "white"
},
{
    "name": "Lectus euismod ut.",
    "ipfsImage": "https://source.unsplash.com/user/erondu/200x300",
    "hair": "coral",
    "skin": "darkgoldenrod"
},
{
    "name": "Sodales mollis eget.",
    "ipfsImage": "https://source.unsplash.com/user/erondu/200x300",
    "hair": "deeppink",
    "skin": "sienna"
},
{
    "name": "Sapien consequat sem.",
    "ipfsImage": "https://source.unsplash.com/user/erondu/200x300",
    "hair": "oldlace",
    "skin": "azure"
},
{
    "name": "Lacus scelerisque lacus.",
    "ipfsImage": "https://source.unsplash.com/user/erondu/200x300",
    "hair": "white",
    "skin": "crimson"
},
{
    "name": "Est sed metus.",
    "ipfsImage": "https://source.unsplash.com/user/erondu/200x300",
    "hair": "lightgreen",
    "skin": "tomato"
},
{
    "name": "Tristique enim lorem.",
    "ipfsImage": "https://source.unsplash.com/user/erondu/200x300",
    "hair": "gainsboro",
    "skin": "beige"
},
{
    "name": "Nam ali elit.",
    "ipfsImage": "https://source.unsplash.com/user/erondu/200x300",
    "hair": "plum",
    "skin": "lawngreen"
},
{
    "name": "El magna vel.",
    "ipfsImage": "https://source.unsplash.com/user/erondu/200x300",
    "hair": "peachpuff",
    "skin": "purple"
},
{
    "name": "Finibus orci dignissim.",
    "ipfsImage": "https://source.unsplash.com/user/erondu/200x300",
    "hair": "gray",
    "skin": "lightpink"
},
{
    "name": "Placerat sapien pellentesque.",
    "ipfsImage": "https://source.unsplash.com/user/erondu/200x300",
    "hair": "seashell",
    "skin": "olive"
},
{
    "name": "Morbi sapien elementum.",
    "ipfsImage": "https://source.unsplash.com/user/erondu/200x300",
    "hair": "peru",
    "skin": "indigo"
},
{
    "name": "Ligula ac auctor.",
    "ipfsImage": "https://source.unsplash.com/user/erondu/200x300",
    "hair": "seagreen",
    "skin": "orangered"
},
{
    "name": "Tempus tem u.",
    "ipfsImage": "https://source.unsplash.com/user/erondu/200x300",
    "hair": "blanchedalmond",
    "skin": "deepskyblue"
},
{
    "name": "Laoreet sollicitudin risus.",
    "ipfsImage": "https://source.unsplash.com/user/erondu/200x300",
    "hair": "white",
    "skin": "darksalmon"
},
{
    "name": "Au i curabitur.",
    "ipfsImage": "https://source.unsplash.com/user/erondu/200x300",
    "hair": "darkgreen",
    "skin": "tomato"
},
{
    "name": "Turpis sapien porttitor.",
    "ipfsImage": "https://source.unsplash.com/user/erondu/200x300",
    "hair": "lightyellow",
    "skin": "forestgreen"
},
{
    "name": "Sed etiam pulvinar.",
    "ipfsImage": "https://source.unsplash.com/user/erondu/200x300",
    "hair": "oldlace",
    "skin": "deepskyblue"
},
{
    "name": "In vitae dia.",
    "ipfsImage": "https://source.unsplash.com/user/erondu/200x300",
    "hair": "darkblue",
    "skin": "palevioletred"
},
{
    "name": "Tristique vitae cit.",
    "ipfsImage": "https://source.unsplash.com/user/erondu/200x300",
    "hair": "crimson",
    "skin": "mediumorchid"
},
{
    "name": "Facilisis iaculis leo.",
    "ipfsImage": "https://source.unsplash.com/user/erondu/200x300",
    "hair": "darkblue",
    "skin": "lavender"
},
{
    "name": "Sagittis tem arcu.",
    "ipfsImage": "https://source.unsplash.com/user/erondu/200x300",
    "hair": "goldenrod",
    "skin": "darkturquoise"
},
{
    "name": "Leo en elit.",
    "ipfsImage": "https://source.unsplash.com/user/erondu/200x300",
    "hair": "sienna",
    "skin": "yellowgreen"
},
{
    "name": "Au placerat pretium.",
    "ipfsImage": "https://source.unsplash.com/user/erondu/200x300",
    "hair": "lime",
    "skin": "mediumturquoise"
}
]
